Affy_ETL/AETL.py
Affy_ETL/__init__.py
Affy_ETL-0.0.6.dist-info/LICENSE
Affy_ETL-0.0.6.dist-info/METADATA
Affy_ETL-0.0.6.dist-info/WHEEL
Affy_ETL-0.0.6.dist-info/top_level.txt
Affy_ETL-0.0.6.dist-info/RECORD
