Metadata-Version: 2.1
Name: Affy-ETL
Version: 0.0.6
Summary: Affydata ETL package
Home-page: https://github.com/dapingtai/Affy-ETL
Author: Hung Chang
Author-email: zero102x@gmail.com
License: UNKNOWN
Platform: UNKNOWN
Requires-Python: >=3.6
